tcex_app_testing/__init__.py
tcex_app_testing/__metadata__.py
tcex_app_testing/registry.py
tcex_app_testing/app/__init__.py
tcex_app_testing/app/app.py
tcex_app_testing/app/config/__init__.py
tcex_app_testing/app/config/app_spec_yml.py
tcex_app_testing/app/config/install_json.py
tcex_app_testing/app/config/install_json_update.py
tcex_app_testing/app/config/install_json_validate.py
tcex_app_testing/app/config/job_json.py
tcex_app_testing/app/config/layout_json.py
tcex_app_testing/app/config/permutation.py
tcex_app_testing/app/config/tcex_json.py
tcex_app_testing/app/config/tcex_json_update.py
tcex_app_testing/app/config/model/__init__.py
tcex_app_testing/app/config/model/app_spec_yml_model.py
tcex_app_testing/app/config/model/install_json_model.py
tcex_app_testing/app/config/model/job_json_model.py
tcex_app_testing/app/config/model/layout_json_model.py
tcex_app_testing/app/config/model/tcex_json_model.py
tcex_app_testing/app/key_value_store/__init__.py
tcex_app_testing/app/key_value_store/key_value_abc.py
tcex_app_testing/app/key_value_store/key_value_api.py
tcex_app_testing/app/key_value_store/key_value_mock.py
tcex_app_testing/app/key_value_store/key_value_redis.py
tcex_app_testing/app/key_value_store/key_value_store.py
tcex_app_testing/app/key_value_store/redis_client.py
tcex_app_testing/app/key_value_store/redis_client_ssl.py
tcex_app_testing/app/playbook/__init__.py
tcex_app_testing/app/playbook/advanced_request.py
tcex_app_testing/app/playbook/playbook.py
tcex_app_testing/app/playbook/playbook_create.py
tcex_app_testing/app/playbook/playbook_delete.py
tcex_app_testing/app/playbook/playbook_output.py
tcex_app_testing/app/playbook/playbook_read.py
tcex_app_testing/cli/__init__.py
tcex_app_testing/cli/cli.py
tcex_app_testing/cli/cli_abc.py
tcex_app_testing/cli/cli_common.py
tcex_app_testing/cli/create.py
tcex_app_testing/cli/negative.py
tcex_app_testing/cli/update.py
tcex_app_testing/config_model/__init__.py
tcex_app_testing/config_model/config_model.py
tcex_app_testing-1.0.1.dist-info/METADATA
tcex_app_testing-1.0.1.dist-info/WHEEL
tcex_app_testing-1.0.1.dist-info/entry_points.txt
tcex_app_testing-1.0.1.dist-info/top_level.txt
tcex_app_testing-1.0.1.dist-info/RECORD
